LICENSE
MANIFEST.in
README.rst
setup.py
version.log
mlpaper/__init__.py
mlpaper/boot_util.py
mlpaper/classification.py
mlpaper/constants.py
mlpaper/data_splitter.py
mlpaper/mlpaper.py
mlpaper/perf_curves.py
mlpaper/regression.py
mlpaper/sciprint.py
mlpaper/test_constants.py
mlpaper/util.py
mlpaper.egg-info/PKG-INFO
mlpaper.egg-info/SOURCES.txt
mlpaper.egg-info/dependency_links.txt
mlpaper.egg-info/requires.txt
mlpaper.egg-info/top_level.txt
requirements/base.in
requirements/demo.in
requirements/test.in