Metadata-Version: 2.1
Name: mlpaper
Version: 0.0.3
Summary: Easy benchmarking of machine learning models with sklearn interface with statistical tests built-in.
Home-page: https://github.com/rdturnermtl/mlpaper/
Author: Ryan Turner
Author-email: rdturnermtl@github.com
License: Apache v2
Platform: any
Requires-Python: >=3.5
Provides-Extra: demo
Provides-Extra: test
